{
  "type": "create:mixing",
  "ingredients": [
    {
      "item": "minecraft:stone_bricks"
    },
    {
      "item": "minecraft:stone_bricks"
    },
    {
      "item": "minecraft:stone_bricks"
    },
    {
      "item": "minecraft:stone_bricks"
    },
    {
      "item": "minecraft:cobblestone"
    },
    {
      "item": "minecraft:cobblestone"
    },
    {
      "item": "minecraft:cobblestone"
    },
    {
      "item": "minecraft:cobblestone"
    },
    {
      "item": "minecraft:chest"
    }
  ],
  "results": [
    {
      "item": "droid_create_ss_crate:starter_crate",
      "count": 1
    }
  ]
}